dagster_qcloud_cos/__init__.py
dagster_qcloud_cos/operations.py
dagster_qcloud_cos/py.typed
dagster_qcloud_cos/resources.py
dagster_qcloud_cos/version.py
dagster_qcloud_cos-0.27.4.dist-info/METADATA
dagster_qcloud_cos-0.27.4.dist-info/WHEEL
dagster_qcloud_cos-0.27.4.dist-info/RECORD
