Metadata-Version: 2.4
Name: dagster-qcloud-cos
Version: 0.27.4
Summary: 腾讯云对象存储与 Dagster 集成
Author-email: YiZixuan <sqkkyzx@qq.com>
Requires-Python: >=3.12
Requires-Dist: anyio
Requires-Dist: cos-python-sdk-v5
Requires-Dist: dagster>=1.11.4
Requires-Dist: docstring-parser
Requires-Dist: httpx
Requires-Dist: pydantic
Requires-Dist: rx
Requires-Dist: tzlocal
Requires-Dist: watchdog
